rsp/__init__.py
rsp/rsp.py
sch_ossc_rsp-1.1.0.dist-info/LICENSE
sch_ossc_rsp-1.1.0.dist-info/METADATA
sch_ossc_rsp-1.1.0.dist-info/WHEEL
sch_ossc_rsp-1.1.0.dist-info/top_level.txt
sch_ossc_rsp-1.1.0.dist-info/RECORD
