Metadata-Version: 2.1
Name: sch-ossc-rsp
Version: 1.1.0
Summary: 가위바위보 프로그램
Author-email: 전한결 <junhg0211@sch.ac.kr>, 정지원 <imprayer1@naver.com>, 방제영 <bjy78910@sch.ac.kr>, 김정훈 <joshuakjh.b612@gmail.com>, 장준서 <junseo12154@naver.com>
Project-URL: Homepage, https://github.com/andrewjeongtheawesome/rsp
Project-URL: Bug Tracker, https://github.com/andrewjeongtheawesome/rsp/issues
Classifier: Programming Language :: Python :: 3
Classifier: License :: OSI Approved :: MIT License
Classifier: Operating System :: OS Independent
Requires-Python: >=3.7
License-File: LICENSE
